customer_dna/__init__.py
customer_dna/association_rules.py
customer_dna/cltv.py
customer_dna/cluster_scoring.py
customer_dna/customer_attrition.py
customer_dna/customer_segmentation.py
customer_dna/data_preprocessing.py
customer_dna/feature_engineering.py
customer_dna/main.py
customer_dna/mba.py
customer_dna/visualisation.py
Customer_dna-0.1.2.dist-info/LICENSE
Customer_dna-0.1.2.dist-info/METADATA
Customer_dna-0.1.2.dist-info/WHEEL
Customer_dna-0.1.2.dist-info/top_level.txt
Customer_dna-0.1.2.dist-info/RECORD
