Metadata-Version: 2.1
Name: Customer_dna
Version: 0.1.2
Summary: A customer analysis package for data
Home-page: 
Author: Phalguni
Author-email: phalgunishenoy2002@gmail.com
Classifier: Programming Language :: Python :: 3
Classifier: License :: OSI Approved :: MIT License
Classifier: Operating System :: OS Independent
Requires-Python: >=3.6
License-File: LICENSE
